odoo/addons/stock_account_show_automatic_valuation/README.rst
odoo/addons/stock_account_show_automatic_valuation/__init__.py
odoo/addons/stock_account_show_automatic_valuation/__manifest__.py
odoo/addons/stock_account_show_automatic_valuation/i18n/it.po
odoo/addons/stock_account_show_automatic_valuation/i18n/stock_account_show_automatic_valuation.pot
odoo/addons/stock_account_show_automatic_valuation/readme/CONTRIBUTORS.md
odoo/addons/stock_account_show_automatic_valuation/readme/DESCRIPTION.md
odoo/addons/stock_account_show_automatic_valuation/readme/USAGE.md
odoo/addons/stock_account_show_automatic_valuation/static/description/icon.png
odoo/addons/stock_account_show_automatic_valuation/static/description/index.html
odoo/addons/stock_account_show_automatic_valuation/tests/__init__.py
odoo/addons/stock_account_show_automatic_valuation/tests/test_res_config_settings.py
odoo/addons/stock_account_show_automatic_valuation/views/res_config_settings_views.xml
odoo_addon_stock_account_show_automatic_valuation-18.0.1.0.0.2.dist-info/METADATA
odoo_addon_stock_account_show_automatic_valuation-18.0.1.0.0.2.dist-info/WHEEL
odoo_addon_stock_account_show_automatic_valuation-18.0.1.0.0.2.dist-info/top_level.txt
odoo_addon_stock_account_show_automatic_valuation-18.0.1.0.0.2.dist-info/RECORD
